{
  "levels": [
    {
      "levelName": "Level 1",
      "url": "https://kdata1.com/2024/09/incredibox-sprunki/?key=y8&value=default",
      "imageUrl": "https://example.com/image1.png"
    },
    {
      "levelName": "Level 2",
      "url": "https://kdata1.com/2024/09/incredibox-sprunki/?key=y8&value=default",
      "imageUrl": "https://example.com/image2.png"
    },
    {
      "levelName": "Level 3",
      "url": "https://kdata1.com/2024/09/incredibox-sprunki/?key=y8&value=default",
      "imageUrl": "https://example.com/image3.png"
    }
  ]
}
